siard_sqlite/__init__.py
siard_sqlite/converter.py
siard_sqlite-0.1.0.dist-info/licenses/LICENSE
siard_sqlite-0.1.0.dist-info/METADATA
siard_sqlite-0.1.0.dist-info/WHEEL
siard_sqlite-0.1.0.dist-info/entry_points.txt
siard_sqlite-0.1.0.dist-info/top_level.txt
siard_sqlite-0.1.0.dist-info/RECORD
