Metadata-Version: 2.4
Name: siard-sqlite
Version: 0.1.0
Summary: Convert SIARD files to SQLite databases for analysis and exploration
Author-email: Henrik Vitalis <henrik.vitalis@vitalibus.se>
Maintainer-email: Henrik Vitalis <henrik.vitalis@vitalibus.se>
License: MIT License
Project-URL: Homepage, https://github.com/svkau/siard-sqlite
Project-URL: Documentation, https://github.com/svkau/siard-sqlite#readme
Project-URL: Repository, https://github.com/svkau/siard-sqlite
Project-URL: Issues, https://github.com/svkau/siard-sqlite/issues
Project-URL: Changelog, https://github.com/svkau/siard-sqlite/releases
Keywords: siard,sqlite,database,converter,archive,xml,data-analysis,data-migration
Classifier: Development Status :: 2 - Pre-Alpha
Classifier: Intended Audience :: Developers
Classifier: Intended Audience :: Information Technology
Classifier: Intended Audience :: Science/Research
Classifier: License :: OSI Approved :: MIT License
Classifier: Operating System :: OS Independent
Classifier: Programming Language :: Python :: 3
Classifier: Programming Language :: Python :: 3.12
Classifier: Programming Language :: Python :: 3.13
Classifier: Topic :: Database :: Front-Ends
Classifier: Topic :: Scientific/Engineering :: Information Analysis
Classifier: Topic :: Software Development :: Libraries :: Python Modules
Classifier: Topic :: Utilities
Requires-Python: >=3.12
License-File: LICENSE
Requires-Dist: lxml>=6.0.0
Provides-Extra: dev
Requires-Dist: pytest>=7.0; extra == "dev"
Requires-Dist: pytest-cov>=4.0; extra == "dev"
Requires-Dist: black>=23.0; extra == "dev"
Requires-Dist: isort>=5.0; extra == "dev"
Requires-Dist: mypy>=1.0; extra == "dev"
Dynamic: license-file
